eznf/__init__.py
eznf/modeler.py
eznf_bersub-0.1.1.dist-info/LICENSE
eznf_bersub-0.1.1.dist-info/METADATA
eznf_bersub-0.1.1.dist-info/WHEEL
eznf_bersub-0.1.1.dist-info/top_level.txt
eznf_bersub-0.1.1.dist-info/RECORD
