Metadata-Version: 2.1
Name: eznf_bersub
Version: 0.1.1
Summary: A prototype library to prototype SAT encodings
Author: Bernardo Subercaseaux
Author-email: Bernardo Subercaseaux <bernardosubercaseaux@gmail.com>
Project-URL: Homepage, https://github.com/bsubercaseaux/eznf
Classifier: Programming Language :: Python :: 3
Classifier: License :: OSI Approved :: MIT License
Classifier: Operating System :: OS Independent
Requires-Python: >=3.7
License-File: LICENSE
